optplus/__init__.py
optplus-0.2.dist-info/METADATA
optplus-0.2.dist-info/RECORD
optplus-0.2.dist-info/WHEEL
optplus-0.2.dist-info/top_level.txt
optplus-0.2.dist-info/zip-safe
