Metadata-Version: 2.1
Name: optplus
Version: 0.2
Summary: additional options for optparse
Home-page: http://noble.gs.washington.edu/~mmh1/software/optplus/
Author: Michael Hoffman
Author-email: mmh1@washington.edu
License: UNKNOWN
Download-URL: http://noble.gs.washington.edu/~mmh1/software/optplus/optplus-0.2.tar.gz
Platform: UNKNOWN
Classifier: Natural Language :: English
Classifier: Programming Language :: Python
